puan_pv_sdk_python/__init__.py
puan_pv_sdk_python-0.1.5.dist-info/METADATA
puan_pv_sdk_python-0.1.5.dist-info/WHEEL
puan_pv_sdk_python-0.1.5.dist-info/RECORD
